financelite/__init__.py
financelite/exceptions.py
financelite/financelite.py
tests/__init__.py
tests/test_group.py
tests/test_news.py
tests/test_stock.py
financelite-0.1.7.dist-info/LICENSE
financelite-0.1.7.dist-info/METADATA
financelite-0.1.7.dist-info/WHEEL
financelite-0.1.7.dist-info/top_level.txt
financelite-0.1.7.dist-info/RECORD
