Metadata-Version: 2.1
Name: financelite
Version: 0.1.7
Summary: A lightweight stock information package for simple tasks
Home-page: https://github.com/d-aughter/financelite
Author: arta
Author-email: arta@a-certain-scientific.tech
License: UNKNOWN
Project-URL: Bug Tracker, https://github.com/d-aughter/financelite/issues
Platform: UNKNOWN
Classifier: Programming Language :: Python :: 3
Classifier: License :: OSI Approved :: GNU General Public License v3 (GPLv3)
Classifier: Operating System :: OS Independent
Requires-Python: >=3.6
License-File: LICENSE
Requires-Dist: feedparser
Requires-Dist: requests
